README.rst
setup.py
json_log_parse/Column.py
json_log_parse/__init__.py
json_log_parse/__main__.py
json_log_parse.egg-info/PKG-INFO
json_log_parse.egg-info/SOURCES.txt
json_log_parse.egg-info/dependency_links.txt
json_log_parse.egg-info/entry_points.txt
json_log_parse.egg-info/requires.txt
json_log_parse.egg-info/top_level.txt